viewclust/__init__.py
viewclust/_version.py
viewclust/cumu_plot.py
viewclust/get_users_run.py
viewclust/insta_plot.py
viewclust/job_use.py
viewclust/node_use.py
viewclust/target_series.py
viewclust/to_terminal.py
viewclust/slurm/__init__.py
viewclust/slurm/mem_info.py
viewclust/slurm/sacct_jobs.py
viewclust-0.8.0.dist-info/AUTHORS.rst
viewclust-0.8.0.dist-info/LICENSE
viewclust-0.8.0.dist-info/METADATA
viewclust-0.8.0.dist-info/WHEEL
viewclust-0.8.0.dist-info/top_level.txt
viewclust-0.8.0.dist-info/RECORD
