Metadata-Version: 2.1
Name: viewclust
Version: 0.8.0
Summary: Python package for visualizing cluster measures.
Home-page: https://github.com/Andesha/viewclust
Author: Tyler Collins
Author-email: tk11br@sharcnet.ca
License: MIT license
Keywords: viewclust
Platform: UNKNOWN
Classifier: Development Status :: 2 - Pre-Alpha
Classifier: Intended Audience :: Developers
Classifier: License :: OSI Approved :: MIT License
Classifier: Natural Language :: English
Classifier: Programming Language :: Python :: 3
Classifier: Programming Language :: Python :: 3.7
Requires-Python: >=3.5
License-File: LICENSE
License-File: AUTHORS.rst
Requires-Dist: numpy
Requires-Dist: pandas
Requires-Dist: plotille
Requires-Dist: plotly
